better_functools/__init__.py
better_functools/apply.py
better_functools/helpers.py
better_functools/pipe.py
better_functools/py.typed
better_functools/strict/__init__.py
better_functools/strict/builtins.py
better_functools/strict/operator.py
better_functools-0.2.0.dist-info/METADATA
better_functools-0.2.0.dist-info/WHEEL
better_functools-0.2.0.dist-info/licenses/LICENSE
better_functools-0.2.0.dist-info/RECORD
